ggpython/__init__.py
ggpython/analysis.py
ggpython/core.py
ggpython/tracker.py
ggpython/utils.py
ggpython/tracker/__init__.py
ggpython/tracker/tracker.py
ggpython/tracker/valorant.py
ggpython-0.0.1.dist-info/LICENSE
ggpython-0.0.1.dist-info/METADATA
ggpython-0.0.1.dist-info/WHEEL
ggpython-0.0.1.dist-info/top_level.txt
ggpython-0.0.1.dist-info/RECORD
