Metadata-Version: 2.1
Name: ggpython
Version: 0.0.1
Summary: Tracker Network Wrapper In Python.
Home-page: https://github.com/nakashimas/ggpython
Author: nakashimas
Author-email: nascor.neco@gmail.com
License: MIT License Copyright (c) 2022 ggpython authors
Keywords: game tracker valorant
Classifier: Development Status :: 1 - Planning
Classifier: License :: OSI Approved :: MIT License
Classifier: Programming Language :: Python
Classifier: Programming Language :: Python :: 3.8
Classifier: Programming Language :: Python :: 3.9
Classifier: Programming Language :: Python :: 3.10
Classifier: Operating System :: POSIX
Classifier: Operating System :: Microsoft :: Windows
Classifier: Operating System :: MacOS :: MacOS X
Classifier: Topic :: Software Development :: Libraries
Classifier: Topic :: Utilities
License-File: LICENSE
Requires-Dist: selenium
Requires-Dist: chromedriver-binary
Requires-Dist: chromedriver-autoinstaller
